winrt_ocr_python-0.1.1.dist-info/licenses/LICENSE
winrtocr/__init__.py
winrtocr/main.py
winrtocr/utils.py
winrt_ocr_python-0.1.1.dist-info/METADATA
winrt_ocr_python-0.1.1.dist-info/WHEEL
winrt_ocr_python-0.1.1.dist-info/top_level.txt
winrt_ocr_python-0.1.1.dist-info/RECORD
