Metadata-Version: 2.4
Name: winrt-ocr-python
Version: 0.1.1
Summary: Python wrapper for OCR by Windows Runtime API
Author-email: Le Hien Hieu <hieulh.work@example.com>
License-Expression: Apache-2.0
Project-URL: Homepage, https://github.com/hieulhaiwork/winrt-ocr-python
Project-URL: Issues, https://github.com/hieulhaiwork/winrt-ocr-python/issues
Classifier: Programming Language :: Python :: 3
Classifier: Operating System :: Microsoft :: Windows :: Windows 10
Classifier: Operating System :: Microsoft :: Windows :: Windows 11
Classifier: Environment :: Win32 (MS Windows)
Classifier: Intended Audience :: Developers
Classifier: Topic :: Software Development :: Libraries :: Python Modules
Classifier: Topic :: Multimedia :: Graphics :: Capture :: Scanners
Requires-Python: >=3.8
License-File: LICENSE
Requires-Dist: winsdk
Requires-Dist: numpy
Requires-Dist: opencv-python
Requires-Dist: pillow
Dynamic: license-file
